3RDPARTYLICENSES
LICENSE
MANIFEST.in
README.rst
setup.py
django_tastypie_swagger_ng.egg-info/PKG-INFO
django_tastypie_swagger_ng.egg-info/SOURCES.txt
django_tastypie_swagger_ng.egg-info/dependency_links.txt
django_tastypie_swagger_ng.egg-info/not-zip-safe
django_tastypie_swagger_ng.egg-info/top_level.txt
tastypie_swagger/__init__.py
tastypie_swagger/mapping.py
tastypie_swagger/urls.py
tastypie_swagger/utils.py
tastypie_swagger/views.py
tastypie_swagger/static/tastypie_swagger/css/hightlight.default.css
tastypie_swagger/static/tastypie_swagger/css/screen.css
tastypie_swagger/static/tastypie_swagger/images/logo_small.png
tastypie_swagger/static/tastypie_swagger/images/pet_store_api.png
tastypie_swagger/static/tastypie_swagger/images/throbber.gif
tastypie_swagger/static/tastypie_swagger/images/wordnik_api.png
tastypie_swagger/static/tastypie_swagger/js/swagger-ui.js
tastypie_swagger/static/tastypie_swagger/js/swagger-ui.min.js
tastypie_swagger/static/tastypie_swagger/js/lib/backbone-min.js
tastypie_swagger/static/tastypie_swagger/js/lib/handlebars-1.0.rc.1.js
tastypie_swagger/static/tastypie_swagger/js/lib/highlight.7.3.pack.js
tastypie_swagger/static/tastypie_swagger/js/lib/jquery-1.8.0.min.js
tastypie_swagger/static/tastypie_swagger/js/lib/jquery.ba-bbq.min.js
tastypie_swagger/static/tastypie_swagger/js/lib/jquery.slideto.min.js
tastypie_swagger/static/tastypie_swagger/js/lib/jquery.wiggle.min.js
tastypie_swagger/static/tastypie_swagger/js/lib/swagger.js
tastypie_swagger/static/tastypie_swagger/js/lib/underscore-min.js
tastypie_swagger/templates/tastypie_swagger/index.html