Metadata-Version: 1.1
Name: django-tastypie-swagger-ng
Version: 0.1.2
Summary: An adapter to use swagger-ui with django-tastypie
Home-page: https://github.com/ifanrx/django-tastypie-swagger
Author: ifanr
Author-email: adamwen@ifanr.com
License: BSD
Download-URL: https://github.com/ifanrx/django-tastypie-swagger/downloads
Platform: UNKNOWN
Classifier: Programming Language :: Python
Classifier: Environment :: Web Environment
Classifier: Framework :: Django
